golden_qlib_alpha/__init__.py
golden_qlib_alpha/common.py
golden_qlib_alpha/config.py
golden_qlib_alpha/alpha/__init__.py
golden_qlib_alpha/alpha/alphalens_utils.py
golden_qlib_alpha/data/__init__.py
golden_qlib_alpha/data/data_update.py
golden_qlib_alpha/data/hdf5/__init__.py
golden_qlib_alpha/datafeed/__init__.py
golden_qlib_alpha/datafeed/datafeed_hdf5.py
golden_qlib_alpha/datafeed/dataloader.py
golden_qlib_alpha/datafeed/dataset.py
golden_qlib_alpha/datafeed/efinance_download.py
golden_qlib_alpha/datafeed/ts_downloader.py
golden_qlib_alpha/datafeed/expr/__init__.py
golden_qlib_alpha/datafeed/expr/base.py
golden_qlib_alpha/datafeed/expr/expr_extend.py
golden_qlib_alpha/datafeed/expr/expr_mgr.py
golden_qlib_alpha/datafeed/expr/ops.py
golden_qlib_alpha/tests/__init__.py
golden_qlib_alpha/tests/test_data_update.py
golden_qlib_alpha/tests/test_loaddata.py
golden_qlib_alpha-0.0.5.dist-info/LICENSE.txt
golden_qlib_alpha-0.0.5.dist-info/METADATA
golden_qlib_alpha-0.0.5.dist-info/WHEEL
golden_qlib_alpha-0.0.5.dist-info/top_level.txt
golden_qlib_alpha-0.0.5.dist-info/RECORD
