Metadata-Version: 2.1
Name: golden_qlib_alpha
Version: 0.0.5
Summary: Separate the qlib factor calculation for independent use and simplify its usage.
Author: gquant
Project-URL: Homepage, https://github.com/yourusername/golden_qlib_alpha
Project-URL: Bug Tracker, https://github.com/yourusername/golden_qlib_alpha/issues
Classifier: Programming Language :: Python :: 3
Classifier: License :: OSI Approved :: MIT License
Classifier: Operating System :: OS Independent
License-File: LICENSE.txt
Requires-Dist: numpy
Requires-Dist: pandas
Requires-Dist: efinance
Requires-Dist: loguru
Requires-Dist: statsmodels
Requires-Dist: tushare
